clarify/__init__.py
clarify/jurisdiction.py
clarify/parser.py
clarify/version.py
clarify-0.7.0.dist-info/licenses/AUTHORS.rst
clarify-0.7.0.dist-info/licenses/LICENSE.txt
clarify-0.7.0.dist-info/METADATA
clarify-0.7.0.dist-info/WHEEL
clarify-0.7.0.dist-info/top_level.txt
clarify-0.7.0.dist-info/RECORD
