Metadata-Version: 2.4
Name: Clarify
Version: 0.7.0
Summary: A Python package for parsing election results from Clarity systems
Author-email: Derek Willis <openelections@gmail.com>
License: MIT
Project-URL: Homepage, https://github.com/openelections/clarify
Project-URL: Repository, https://github.com/openelections/clarify
Project-URL: Issues, https://github.com/openelections/clarify/issues
Keywords: elections,Clarity,results,parser,scraper
Classifier: Development Status :: 4 - Beta
Classifier: License :: OSI Approved :: MIT License
Classifier: Operating System :: OS Independent
Classifier: Programming Language :: Python
Classifier: Programming Language :: Python :: 3
Classifier: Programming Language :: Python :: 3.8
Classifier: Programming Language :: Python :: 3.9
Classifier: Programming Language :: Python :: 3.10
Classifier: Programming Language :: Python :: 3.11
Classifier: Programming Language :: Python :: 3.12
Classifier: Topic :: Internet
Classifier: Topic :: Internet :: WWW/HTTP
Classifier: Topic :: Text Processing
Classifier: Topic :: Text Processing :: Markup :: XML
Requires-Python: >=3.8
License-File: LICENSE.txt
License-File: AUTHORS.rst
Requires-Dist: requests>=2.31.0
Requires-Dist: cssselect>=1.2.0
Requires-Dist: requests-futures>=1.0.1
Requires-Dist: wheel>=0.40.0
Requires-Dist: lxml>=4.9.0
Requires-Dist: python-dateutil>=2.8.2
Requires-Dist: build>=1.2.2.post1
Requires-Dist: twine>=6.1.0
Provides-Extra: dev
Requires-Dist: pytest>=6.0.0; extra == "dev"
Requires-Dist: responses>=0.20.0; extra == "dev"
Requires-Dist: codecov; extra == "dev"
Requires-Dist: coverage; extra == "dev"
Dynamic: license-file
